pydol/__init__.py
pydol/pydol.py
pydol-1.0.3.dist-info/DESCRIPTION.rst
pydol-1.0.3.dist-info/METADATA
pydol-1.0.3.dist-info/RECORD
pydol-1.0.3.dist-info/WHEEL
pydol-1.0.3.dist-info/metadata.json
pydol-1.0.3.dist-info/top_level.txt
