Metadata-Version: 2.0
Name: pydol
Version: 1.0.3
Summary: A pythonic interface to the U.S. Department of Labor API
Home-page: https://github.com/seanthegeek/pydol
Author: Sean Whalen
Author-email: whalenster@gmail.com
License: Apache 2.0
Keywords: DoL USDoL BLS statistics API
Platform: UNKNOWN
Classifier: Development Status :: 5 - Production/Stable
Classifier: Intended Audience :: Developers
Classifier: Intended Audience :: Education
Classifier: Intended Audience :: Science/Research
Classifier: Intended Audience :: Legal Industry
Classifier: Operating System :: OS Independent
Classifier: License :: OSI Approved :: Apache Software License
Classifier: Programming Language :: Python :: 2
Classifier: Programming Language :: Python :: 2.6
Classifier: Programming Language :: Python :: 2.7
Classifier: Programming Language :: Python :: 3
Classifier: Programming Language :: Python :: 3.3
Classifier: Programming Language :: Python :: 3.4
Classifier: Programming Language :: Python :: 3.5
Requires-Dist: requests
Requires-Dist: xmltodict
Provides-Extra: test
Requires-Dist: nose; extra == 'test'
